{
    "boxShadow": "none",
    "mobileBottomRow": 13,
    "widgetName": "Image1",
    "displayName": "Image",
    "iconSVG": "https://appcdn.appsmith.com/static/media/icon.69b0f0dd810281fbd6e34fc2c3f39344.svg",
    "topRow": 3,
    "bottomRow": 17,
    "parentRowSpace": 10,
    "type": "IMAGE_WIDGET",
    "hideCard": false,
    "mobileRightColumn": 36,
    "animateLoading": true,
    "parentColumnSpace": 6.84375,
    "dynamicTriggerPathList": [],
    "imageShape": "RECTANGLE",
    "leftColumn": 15,
    "dynamicBindingPathList": [{"key": "borderRadius"}],
    "defaultImage": "https://i.pinimg.com/originals/9b/15/8a/9b158a49e59055265b35b38a51b1cbc6.jpg",
    "key": "qe4160qnax",
    "image": "https://i.pinimg.com/originals/9b/15/8a/9b158a49e59055265b35b38a51b1cbc6.jpg",
    "isDeprecated": false,
    "rightColumn": 46,
    "objectFit": "cover",
    "widgetId": "aiezdpxdrd",
    "isVisible": true,
    "version": 1,
    "parentId": "0",
    "tags": ["Media"],
    "renderMode": "CANVAS",
    "isLoading": false,
    "mobileTopRow": 1,
    "maxZoomLevel": 1,
    "enableDownload": false,
    "borderRadius": "{{appsmith.theme.borderRadius.appBorderRadius}}",
    "mobileLeftColumn": 24,
    "enableRotation": false
}